{
	"_transient": null,
	"attributes": {
		"AT16_APELLIDD648": {
			"attributeId": "AT16_APELLIDD648",
			"autoGeneratedStr": "F",
			"columnName": null,
			"customizationLayer": 0,
			"customizationLayerDescription": "ECU",
			"dataType": "String",
			"entityPk": {
				"entityId": "EN_CLIENTEFM_648",
				"version": "1.0.0"
			},
			"expression": null,
			"falseValue": null,
			"labelId": null,
			"length": 40,
			"listValues": null,
			"name": "apellido",
			"objectType": null,
			"order": 3,
			"pkStr": "F",
			"requiredStr": "T",
			"transientStr": "F",
			"trueValue": null
		},
		"AT61_NACIONAI648": {
			"attributeId": "AT61_NACIONAI648",
			"autoGeneratedStr": "F",
			"columnName": null,
			"customizationLayer": 0,
			"customizationLayerDescription": "ECU",
			"dataType": "String",
			"entityPk": {
				"entityId": "EN_CLIENTEFM_648",
				"version": "1.0.0"
			},
			"expression": null,
			"falseValue": null,
			"labelId": null,
			"length": 0,
			"listValues": null,
			"name": "nacionalidad",
			"objectType": null,
			"order": 6,
			"pkStr": "F",
			"requiredStr": "T",
			"transientStr": "F",
			"trueValue": null
		},
		"AT65_TELEFONO648": {
			"attributeId": "AT65_TELEFONO648",
			"autoGeneratedStr": "F",
			"columnName": null,
			"customizationLayer": 0,
			"customizationLayerDescription": "ECU",
			"dataType": "String",
			"entityPk": {
				"entityId": "EN_CLIENTEFM_648",
				"version": "1.0.0"
			},
			"expression": null,
			"falseValue": null,
			"labelId": null,
			"length": 15,
			"listValues": null,
			"name": "telefono",
			"objectType": null,
			"order": 4,
			"pkStr": "F",
			"requiredStr": "T",
			"transientStr": "F",
			"trueValue": null
		},
		"AT68_CEDULAFG648": {
			"attributeId": "AT68_CEDULAFG648",
			"autoGeneratedStr": "F",
			"columnName": null,
			"customizationLayer": 0,
			"customizationLayerDescription": "ECU",
			"dataType": "String",
			"entityPk": {
				"entityId": "EN_CLIENTEFM_648",
				"version": "1.0.0"
			},
			"expression": null,
			"falseValue": null,
			"labelId": null,
			"length": 20,
			"listValues": null,
			"name": "cedula",
			"objectType": null,
			"order": 5,
			"pkStr": "F",
			"requiredStr": "T",
			"transientStr": "F",
			"trueValue": null
		},
		"AT85_IDCLIETE648": {
			"attributeId": "AT85_IDCLIETE648",
			"autoGeneratedStr": "F",
			"columnName": null,
			"customizationLayer": 0,
			"customizationLayerDescription": "ECU",
			"dataType": "String",
			"entityPk": {
				"entityId": "EN_CLIENTEFM_648",
				"version": "1.0.0"
			},
			"expression": null,
			"falseValue": null,
			"labelId": null,
			"length": 0,
			"listValues": null,
			"name": "idCliente",
			"objectType": null,
			"order": 1,
			"pkStr": "F",
			"requiredStr": "F",
			"transientStr": "F",
			"trueValue": null
		},
		"AT88_NOMBRESK648": {
			"attributeId": "AT88_NOMBRESK648",
			"autoGeneratedStr": "F",
			"columnName": null,
			"customizationLayer": 0,
			"customizationLayerDescription": "ECU",
			"dataType": "String",
			"entityPk": {
				"entityId": "EN_CLIENTEFM_648",
				"version": "1.0.0"
			},
			"expression": null,
			"falseValue": null,
			"labelId": null,
			"length": 40,
			"listValues": null,
			"name": "nombre",
			"objectType": null,
			"order": 2,
			"pkStr": "F",
			"requiredStr": "T",
			"transientStr": "F",
			"trueValue": null
		}
	},
	"customizationLayer": 0,
	"customizationLayerDescription": "ECU",
	"databaseName": null,
	"dbmsName": null,
	"description": null,
	"id": {
		"entityId": "EN_CLIENTEFM_648",
		"version": "1.0.0"
	},
	"isAutomatic": false,
	"isImported": false,
	"moduleId": "MMPPW",
	"name": {
		"$ref": "../../MMPPW/relations/componentKeys.json#/Entities/EN_CLIENTEFM_648/name"
	},
	"related": false,
	"tableName": null,
	"transient": null
}
